napari_cryofibsem_imgpro/__init__.py
napari_cryofibsem_imgpro/_reader.py
napari_cryofibsem_imgpro/_sample_data.py
napari_cryofibsem_imgpro/_widget.py
napari_cryofibsem_imgpro/_writer.py
napari_cryofibsem_imgpro/brightness.py
napari_cryofibsem_imgpro/contrast.py
napari_cryofibsem_imgpro/decharge.py
napari_cryofibsem_imgpro/decurtain.py
napari_cryofibsem_imgpro/denoise.py
napari_cryofibsem_imgpro/napari.yaml
napari_cryofibsem_imgpro/_tests/__init__.py
napari_cryofibsem_imgpro/_tests/test_reader.py
napari_cryofibsem_imgpro/_tests/test_sample_data.py
napari_cryofibsem_imgpro/_tests/test_widget.py
napari_cryofibsem_imgpro/_tests/test_writer.py
napari_cryofibsem_imgpro-0.0.1.dist-info/LICENSE
napari_cryofibsem_imgpro-0.0.1.dist-info/METADATA
napari_cryofibsem_imgpro-0.0.1.dist-info/WHEEL
napari_cryofibsem_imgpro-0.0.1.dist-info/entry_points.txt
napari_cryofibsem_imgpro-0.0.1.dist-info/top_level.txt
napari_cryofibsem_imgpro-0.0.1.dist-info/RECORD
