Metadata-Version: 2.1
Name: napari-cryofibsem-imgpro
Version: 0.0.1
Summary: A napari plugin for post-processing of Cryo-FIB/SEM image stacks
Home-page: https://github.com/shainatorumc/napari-cryofibsem-imgpro
Author: Shaina Vivienne To
Author-email: shaina.to@radboudumc.nl
License: Apache License
Project-URL: Bug Tracker, https://github.com/shainatorumc/napari-cryofibsem-imgpro/issues
Project-URL: Documentation, https://github.com/shainatorumc/napari-cryofibsem-imgpro#README.md
Project-URL: Source Code, https://github.com/shainatorumc/napari-cryofibsem-imgpro
Project-URL: User Support, https://github.com/shainatorumc/napari-cryofibsem-imgpro/issues
Classifier: Development Status :: 2 - Pre-Alpha
Classifier: Framework :: napari
Classifier: Intended Audience :: Developers
Classifier: License :: OSI Approved :: BSD License
Classifier: Operating System :: OS Independent
Classifier: Programming Language :: Python
Classifier: Programming Language :: Python :: 3
Classifier: Programming Language :: Python :: 3 :: Only
Classifier: Programming Language :: Python :: 3.10
Classifier: Programming Language :: Python :: 3.11
Classifier: Programming Language :: Python :: 3.12
Classifier: Topic :: Scientific/Engineering :: Image Processing
Requires-Python: >=3.10
License-File: LICENSE
Requires-Dist: numpy
Requires-Dist: magicgui
Requires-Dist: qtpy
Requires-Dist: scikit-image
Requires-Dist: PyWavelets
Requires-Dist: opencv-python
Provides-Extra: testing
Requires-Dist: tox; extra == "testing"
Requires-Dist: pytest; extra == "testing"
Requires-Dist: pytest-cov; extra == "testing"
Requires-Dist: pytest-qt; extra == "testing"
Requires-Dist: napari; extra == "testing"
Requires-Dist: pyqt5; extra == "testing"
